Multi_donuts/__init__.py
Multi_donuts/multi_donuts.py
Multi_donuts-1.0.dist-info/LICENSE.txt
Multi_donuts-1.0.dist-info/METADATA
Multi_donuts-1.0.dist-info/WHEEL
Multi_donuts-1.0.dist-info/top_level.txt
Multi_donuts-1.0.dist-info/RECORD
